arraylake_client/__init__.py
arraylake_client-0.7.2.dist-info/METADATA
arraylake_client-0.7.2.dist-info/WHEEL
arraylake_client-0.7.2.dist-info/RECORD
